{
    "type": "Feature",
    "properties": {
        "gml_id": "idf3816695-5342-4239-88a5-3c01aa9c3d9d",
        "WD15CD": "W05000144",
        "WD15NM": "Rhiw",
        "WD15NMW": "Rhiw",
        "LAD15CD": "W06000003",
        "LAD15NM": "Conwy"
    },
    "geometry": {
        "type": "MultiPolygon",
        "coordinates": [
            [
                [
                    [
                        -3.7374247658897,
                        53.303849426083
                    ],
                    [
                        -3.7316753731889,
                        53.300144727773
                    ],
                    [
                        -3.7264078208233,
                        53.297609555361
                    ],
                    [
                        -3.7234653546762,
                        53.296793591695
                    ],
                    [
                        -3.7219431658061,
                        53.298567710639
                    ],
                    [
                        -3.7239716835858,
                        53.295952910361
                    ],
                    [
                        -3.7264232442925,
                        53.296355244291
                    ],
                    [
                        -3.7273987181427,
                        53.295057360832
                    ],
                    [
                        -3.7269299322548,
                        53.294744112053
                    ],
                    [
                        -3.728679544773,
                        53.293482648302
                    ],
                    [
                        -3.7301719630022,
                        53.291131720157
                    ],
                    [
                        -3.7289446934882,
                        53.289906222465
                    ],
                    [
                        -3.7218592247579,
                        53.289208665613
                    ],
                    [
                        -3.7202535914472,
                        53.28878954228
                    ],
                    [
                        -3.7213239996302,
                        53.286568874209
                    ],
                    [
                        -3.7224769264928,
                        53.286252858883
                    ],
                    [
                        -3.7223551850408,
                        53.285799729541
                    ],
                    [
                        -3.7229814671327,
                        53.285183862407
                    ],
                    [
                        -3.7246535441971,
                        53.284722776068
                    ],
                    [
                        -3.7273437209258,
                        53.28317262616
                    ],
                    [
                        -3.7280975469263,
                        53.283080792095
                    ],
                    [
                        -3.7287774569907,
                        53.282124297851
                    ],
                    [
                        -3.7305532214261,
                        53.281041320324
                    ],
                    [
                        -3.7307621079804,
                        53.280382923728
                    ],
                    [
                        -3.7318002510607,
                        53.279904866552
                    ],
                    [
                        -3.7318480511349,
                        53.279417818131
                    ],
                    [
                        -3.7336253773811,
                        53.278526255589
                    ],
                    [
                        -3.7337052298001,
                        53.278164598805
                    ],
                    [
                        -3.7352612067408,
                        53.277883049441
                    ],
                    [
                        -3.7356833265629,
                        53.275937778984
                    ],
                    [
                        -3.7363637832308,
                        53.275815495167
                    ],
                    [
                        -3.7371255310297,
                        53.274665373865
                    ],
                    [
                        -3.737554504592,
                        53.273446381075
                    ],
                    [
                        -3.738559495772,
                        53.273044261562
                    ],
                    [
                        -3.7392449692101,
                        53.272160440873
                    ],
                    [
                        -3.7393511956783,
                        53.270861644119
                    ],
                    [
                        -3.7399178176296,
                        53.270523444046
                    ],
                    [
                        -3.7404731715635,
                        53.268874673479
                    ],
                    [
                        -3.7453315927578,
                        53.269017592671
                    ],
                    [
                        -3.7455373693279,
                        53.267553713835
                    ],
                    [
                        -3.7471154224813,
                        53.267530593368
                    ],
                    [
                        -3.7469976395726,
                        53.268540092491
                    ],
                    [
                        -3.7486334132903,
                        53.268828057254
                    ],
                    [
                        -3.7494642816048,
                        53.27037292369
                    ],
                    [
                        -3.7487685167062,
                        53.270704973474
                    ],
                    [
                        -3.7500110071197,
                        53.27222941238
                    ],
                    [
                        -3.7501238653655,
                        53.273780318301
                    ],
                    [
                        -3.7548711894839,
                        53.279213266904
                    ],
                    [
                        -3.7552545912955,
                        53.280626234533
                    ],
                    [
                        -3.7516668611883,
                        53.280008357853
                    ],
                    [
                        -3.7498217143567,
                        53.281838836449
                    ],
                    [
                        -3.7463784282755,
                        53.282960927482
                    ],
                    [
                        -3.7479887421985,
                        53.284595967517
                    ],
                    [
                        -3.7500192500995,
                        53.284029479134
                    ],
                    [
                        -3.7513267277416,
                        53.283977914814
                    ],
                    [
                        -3.7526352356816,
                        53.285050961117
                    ],
                    [
                        -3.7519558086542,
                        53.285640798078
                    ],
                    [
                        -3.751133526035,
                        53.285672657113
                    ],
                    [
                        -3.7509740603002,
                        53.286431951029
                    ],
                    [
                        -3.7512715338631,
                        53.287286119298
                    ],
                    [
                        -3.7530575805503,
                        53.288148073991
                    ],
                    [
                        -3.7521659718288,
                        53.289712841987
                    ],
                    [
                        -3.7502414588706,
                        53.289648514572
                    ],
                    [
                        -3.7493003138781,
                        53.289894267404
                    ],
                    [
                        -3.7476479635945,
                        53.289587671646
                    ],
                    [
                        -3.7468809541508,
                        53.290865591532
                    ],
                    [
                        -3.7481283718914,
                        53.291064863346
                    ],
                    [
                        -3.7477497048985,
                        53.291638577551
                    ],
                    [
                        -3.7491439490815,
                        53.292052343327
                    ],
                    [
                        -3.7487489693517,
                        53.293071300635
                    ],
                    [
                        -3.7500334473005,
                        53.292927493616
                    ],
                    [
                        -3.750337787155,
                        53.294352422214
                    ],
                    [
                        -3.7516278937773,
                        53.294711950808
                    ],
                    [
                        -3.7510793829465,
                        53.296158393939
                    ],
                    [
                        -3.749574815915,
                        53.296793593384
                    ],
                    [
                        -3.7494047626745,
                        53.297185351623
                    ],
                    [
                        -3.7507815912714,
                        53.298415638345
                    ],
                    [
                        -3.7515930317959,
                        53.298699488457
                    ],
                    [
                        -3.7516315702941,
                        53.299127740901
                    ],
                    [
                        -3.7462827393092,
                        53.300106089027
                    ],
                    [
                        -3.7414178148729,
                        53.300369624528
                    ],
                    [
                        -3.7414354026531,
                        53.300801781446
                    ],
                    [
                        -3.7435560488002,
                        53.302242435844
                    ],
                    [
                        -3.7374247658897,
                        53.303849426083
                    ]
                ]
            ]
        ]
    }
}