{
    "type": "Feature",
    "properties": {
        "gml_id": "idbabb9dd1-b894-47b4-a8a0-350535896910",
        "WD15CD": "W05000329",
        "WD15NM": "Llanyre",
        "WD15NMW": "Llanllyr",
        "LAD15CD": "W06000023",
        "LAD15NM": "Powys"
    },
    "geometry": {
        "type": "MultiPolygon",
        "coordinates": [
            [
                [
                    [
                        -3.3895342621027,
                        52.250291963458
                    ],
                    [
                        -3.3903594102758,
                        52.248712421751
                    ],
                    [
                        -3.3892002553985,
                        52.246588018617
                    ],
                    [
                        -3.3887805051046,
                        52.243888473232
                    ],
                    [
                        -3.3893843681636,
                        52.243385962386
                    ],
                    [
                        -3.3945055693478,
                        52.24168020735
                    ],
                    [
                        -3.3945757232199,
                        52.241395263132
                    ],
                    [
                        -3.3878457836094,
                        52.238952631725
                    ],
                    [
                        -3.3874340668066,
                        52.238289442944
                    ],
                    [
                        -3.387962508141,
                        52.238000012649
                    ],
                    [
                        -3.388950351754,
                        52.237884094208
                    ],
                    [
                        -3.390731409352,
                        52.238547331535
                    ],
                    [
                        -3.392190695663,
                        52.237912443465
                    ],
                    [
                        -3.3935662612487,
                        52.235962244384
                    ],
                    [
                        -3.3940394823837,
                        52.233819495084
                    ],
                    [
                        -3.3946961072687,
                        52.233511436668
                    ],
                    [
                        -3.39606193048,
                        52.233171609542
                    ],
                    [
                        -3.4012189585512,
                        52.233299295091
                    ],
                    [
                        -3.4034943601817,
                        52.232736389339
                    ],
                    [
                        -3.4040626687618,
                        52.232138020057
                    ],
                    [
                        -3.4039453777636,
                        52.231576578403
                    ],
                    [
                        -3.4021365789057,
                        52.230820363321
                    ],
                    [
                        -3.4016136285868,
                        52.230163039723
                    ],
                    [
                        -3.4018632035206,
                        52.227581452541
                    ],
                    [
                        -3.4023543720987,
                        52.226673817201
                    ],
                    [
                        -3.4038502159312,
                        52.225869315456
                    ],
                    [
                        -3.4113921797864,
                        52.225650769761
                    ],
                    [
                        -3.4127607847737,
                        52.224533889008
                    ],
                    [
                        -3.4136132808438,
                        52.222611286197
                    ],
                    [
                        -3.4137333740221,
                        52.221138015053
                    ],
                    [
                        -3.4122045724467,
                        52.217433135337
                    ],
                    [
                        -3.4160295221561,
                        52.215269899477
                    ],
                    [
                        -3.4156794719162,
                        52.214572798762
                    ],
                    [
                        -3.4127687422167,
                        52.212240347442
                    ],
                    [
                        -3.4125945683044,
                        52.211225545563
                    ],
                    [
                        -3.4130193355724,
                        52.210313261963
                    ],
                    [
                        -3.4137534577161,
                        52.210156114586
                    ],
                    [
                        -3.415346428215,
                        52.210635118783
                    ],
                    [
                        -3.419351295656,
                        52.211016777105
                    ],
                    [
                        -3.4193534673539,
                        52.210488076922
                    ],
                    [
                        -3.4174110951872,
                        52.209195139029
                    ],
                    [
                        -3.4165501287586,
                        52.208170609544
                    ],
                    [
                        -3.4169114943426,
                        52.207706826911
                    ],
                    [
                        -3.4181682925676,
                        52.207466049838
                    ],
                    [
                        -3.4200290118634,
                        52.208219595573
                    ],
                    [
                        -3.4233222808764,
                        52.207772613691
                    ],
                    [
                        -3.4298634157588,
                        52.210119304566
                    ],
                    [
                        -3.4325713928136,
                        52.210402938238
                    ],
                    [
                        -3.4359213371091,
                        52.211303577471
                    ],
                    [
                        -3.4367892031013,
                        52.209804988707
                    ],
                    [
                        -3.4367682592179,
                        52.208657083566
                    ],
                    [
                        -3.4361149291922,
                        52.208275724968
                    ],
                    [
                        -3.4334913029112,
                        52.208381360698
                    ],
                    [
                        -3.4338977595488,
                        52.206823662652
                    ],
                    [
                        -3.4375925893455,
                        52.204361893007
                    ],
                    [
                        -3.438079529745,
                        52.202673726219
                    ],
                    [
                        -3.4415201906059,
                        52.200830817163
                    ],
                    [
                        -3.4436921981837,
                        52.19831821757
                    ],
                    [
                        -3.4463356368486,
                        52.196858948219
                    ],
                    [
                        -3.4493806824629,
                        52.199563859312
                    ],
                    [
                        -3.450715103528,
                        52.202482151137
                    ],
                    [
                        -3.4520443730282,
                        52.204249630503
                    ],
                    [
                        -3.4566715220896,
                        52.208048867307
                    ],
                    [
                        -3.4557983868215,
                        52.209096318346
                    ],
                    [
                        -3.4530590967146,
                        52.209828697265
                    ],
                    [
                        -3.4488380433748,
                        52.209645944099
                    ],
                    [
                        -3.4472481531359,
                        52.208551463391
                    ],
                    [
                        -3.4460679863365,
                        52.208218879469
                    ],
                    [
                        -3.4445106784688,
                        52.208801699058
                    ],
                    [
                        -3.4431815744295,
                        52.210691706723
                    ],
                    [
                        -3.4431856037932,
                        52.211583572372
                    ],
                    [
                        -3.4457736665962,
                        52.215019743163
                    ],
                    [
                        -3.4484452934041,
                        52.217592587446
                    ],
                    [
                        -3.4480172233232,
                        52.217978164388
                    ],
                    [
                        -3.4458678804747,
                        52.218190639076
                    ],
                    [
                        -3.4450640685788,
                        52.21859159846
                    ],
                    [
                        -3.4433986890649,
                        52.220051454011
                    ],
                    [
                        -3.4431444928424,
                        52.221015708296
                    ],
                    [
                        -3.4460338758921,
                        52.222173445974
                    ],
                    [
                        -3.4475017945904,
                        52.223374634779
                    ],
                    [
                        -3.4480743847306,
                        52.225493995352
                    ],
                    [
                        -3.4472823769192,
                        52.227251574903
                    ],
                    [
                        -3.447320144612,
                        52.228502666925
                    ],
                    [
                        -3.4499360766416,
                        52.231450187344
                    ],
                    [
                        -3.452635318629,
                        52.236444786277
                    ],
                    [
                        -3.4575873189106,
                        52.242900436296
                    ],
                    [
                        -3.4591396803668,
                        52.243653583188
                    ],
                    [
                        -3.462605198832,
                        52.244367729276
                    ],
                    [
                        -3.4648281040557,
                        52.246752456833
                    ],
                    [
                        -3.4655557120119,
                        52.248962413779
                    ],
                    [
                        -3.4685305004253,
                        52.248818441013
                    ],
                    [
                        -3.4713619564794,
                        52.249212946035
                    ],
                    [
                        -3.4728036784896,
                        52.250326936056
                    ],
                    [
                        -3.4698702511751,
                        52.251281493432
                    ],
                    [
                        -3.463815566983,
                        52.254037874451
                    ],
                    [
                        -3.4617857712278,
                        52.255263335506
                    ],
                    [
                        -3.4583217446953,
                        52.258237263732
                    ],
                    [
                        -3.4573181746479,
                        52.258641668151
                    ],
                    [
                        -3.452386011547,
                        52.259841626305
                    ],
                    [
                        -3.4355685201632,
                        52.262755463023
                    ],
                    [
                        -3.4295885087991,
                        52.26457589222
                    ],
                    [
                        -3.4265721500281,
                        52.268664622509
                    ],
                    [
                        -3.427550217627,
                        52.271008434137
                    ],
                    [
                        -3.4285645315919,
                        52.271012346697
                    ],
                    [
                        -3.4297544125074,
                        52.27228185201
                    ],
                    [
                        -3.4279399691865,
                        52.272738079166
                    ],
                    [
                        -3.4283142438521,
                        52.273438443422
                    ],
                    [
                        -3.4294036521145,
                        52.273587993267
                    ],
                    [
                        -3.4295359575407,
                        52.273919057148
                    ],
                    [
                        -3.4270491017795,
                        52.274433760715
                    ],
                    [
                        -3.4262719746732,
                        52.275017675911
                    ],
                    [
                        -3.4227421339487,
                        52.276012415496
                    ],
                    [
                        -3.4198785781758,
                        52.275983057745
                    ],
                    [
                        -3.4178402754281,
                        52.276505656367
                    ],
                    [
                        -3.4164139137167,
                        52.276086718091
                    ],
                    [
                        -3.4156317772854,
                        52.276196798929
                    ],
                    [
                        -3.4150584751499,
                        52.275730748319
                    ],
                    [
                        -3.4097577171651,
                        52.278851094438
                    ],
                    [
                        -3.4079974510078,
                        52.280799761177
                    ],
                    [
                        -3.404692160506,
                        52.280300579674
                    ],
                    [
                        -3.4033429810496,
                        52.279308741466
                    ],
                    [
                        -3.4021834795004,
                        52.279494246534
                    ],
                    [
                        -3.4019676939826,
                        52.279020289593
                    ],
                    [
                        -3.4010517094477,
                        52.279165129343
                    ],
                    [
                        -3.4008260384119,
                        52.278795582578
                    ],
                    [
                        -3.3998305935099,
                        52.278791207073
                    ],
                    [
                        -3.3969689638885,
                        52.277802836113
                    ],
                    [
                        -3.3937438786092,
                        52.27755954102
                    ],
                    [
                        -3.3932143660765,
                        52.278108843941
                    ],
                    [
                        -3.3921639611639,
                        52.277940518426
                    ],
                    [
                        -3.3914343338907,
                        52.278232335106
                    ],
                    [
                        -3.3909636909938,
                        52.277573451776
                    ],
                    [
                        -3.3885519042397,
                        52.277227822555
                    ],
                    [
                        -3.387884284639,
                        52.276971340287
                    ],
                    [
                        -3.3879335698916,
                        52.276672261956
                    ],
                    [
                        -3.3866799944373,
                        52.276567414768
                    ],
                    [
                        -3.3866166181729,
                        52.276180650165
                    ],
                    [
                        -3.3845354767323,
                        52.276187994814
                    ],
                    [
                        -3.3841193946615,
                        52.276429335561
                    ],
                    [
                        -3.3838539351951,
                        52.276142040874
                    ],
                    [
                        -3.3830363319945,
                        52.276339533095
                    ],
                    [
                        -3.3827309892217,
                        52.275759598982
                    ],
                    [
                        -3.3812397653199,
                        52.275929902658
                    ],
                    [
                        -3.3805915041914,
                        52.275162468328
                    ],
                    [
                        -3.3796853340441,
                        52.275103832737
                    ],
                    [
                        -3.3801714177438,
                        52.274662090648
                    ],
                    [
                        -3.380018263376,
                        52.274119930191
                    ],
                    [
                        -3.380497906458,
                        52.273895842357
                    ],
                    [
                        -3.3805253294987,
                        52.273033291675
                    ],
                    [
                        -3.3778915077097,
                        52.271755885114
                    ],
                    [
                        -3.3760735658232,
                        52.26974963757
                    ],
                    [
                        -3.3765079150539,
                        52.268963261456
                    ],
                    [
                        -3.3756469290046,
                        52.26889238029
                    ],
                    [
                        -3.3757518316807,
                        52.268257297103
                    ],
                    [
                        -3.3742796731996,
                        52.267757467637
                    ],
                    [
                        -3.3741201393667,
                        52.267005884956
                    ],
                    [
                        -3.3729019136904,
                        52.266517467547
                    ],
                    [
                        -3.3728890072068,
                        52.265957482662
                    ],
                    [
                        -3.3715889462936,
                        52.265380094316
                    ],
                    [
                        -3.3721609456655,
                        52.265016506219
                    ],
                    [
                        -3.371829209155,
                        52.264666119479
                    ],
                    [
                        -3.3730945144736,
                        52.264166795654
                    ],
                    [
                        -3.3726772568437,
                        52.263562063548
                    ],
                    [
                        -3.3730324755916,
                        52.263107486114
                    ],
                    [
                        -3.3724147214475,
                        52.262510479731
                    ],
                    [
                        -3.3713946725615,
                        52.262409050108
                    ],
                    [
                        -3.3713793899285,
                        52.261913827129
                    ],
                    [
                        -3.3714376907059,
                        52.261049120734
                    ],
                    [
                        -3.3727327600805,
                        52.259666543914
                    ],
                    [
                        -3.3713508410375,
                        52.259374218943
                    ],
                    [
                        -3.3715117181919,
                        52.258984840129
                    ],
                    [
                        -3.3726913066696,
                        52.258466735381
                    ],
                    [
                        -3.3747996305563,
                        52.259270262157
                    ],
                    [
                        -3.3755837180036,
                        52.259229658194
                    ],
                    [
                        -3.3782660403969,
                        52.257514361704
                    ],
                    [
                        -3.3812310524484,
                        52.256604880673
                    ],
                    [
                        -3.3818514208986,
                        52.255541181886
                    ],
                    [
                        -3.378798277038,
                        52.252378806647
                    ],
                    [
                        -3.3794509620943,
                        52.251176281436
                    ],
                    [
                        -3.3810346151905,
                        52.250659661384
                    ],
                    [
                        -3.3815511132209,
                        52.251771192754
                    ],
                    [
                        -3.3823183828477,
                        52.252230637625
                    ],
                    [
                        -3.3835991833357,
                        52.252809032751
                    ],
                    [
                        -3.3854295264389,
                        52.252733615178
                    ],
                    [
                        -3.3876812559327,
                        52.251937534505
                    ],
                    [
                        -3.3891962999566,
                        52.251008925922
                    ],
                    [
                        -3.3895342621027,
                        52.250291963458
                    ]
                ]
            ]
        ]
    }
}