{
    "type": "Feature",
    "properties": {
        "gml_id": "ided705168-fdfb-4123-a52f-ce45044c2198",
        "PAR15CD": "W04000723",
        "PAR15NM": "Troed-y-rhiw",
        "PAR15NMW": "Troed-y-rhiw",
        "LAD15CD": "W06000024",
        "LAD15NM": "Merthyr Tydfil"
    },
    "geometry": {
        "type": "MultiPolygon",
        "coordinates": [
            [
                [
                    [
                        -3.3674926301447,
                        51.698589418452
                    ],
                    [
                        -3.3721948592584,
                        51.702205906444
                    ],
                    [
                        -3.3805921952698,
                        51.711368101828
                    ],
                    [
                        -3.3856910600934,
                        51.715048626419
                    ],
                    [
                        -3.3889008735538,
                        51.716580675742
                    ],
                    [
                        -3.3989830561684,
                        51.718401452294
                    ],
                    [
                        -3.3999035394671,
                        51.717878855667
                    ],
                    [
                        -3.3999439957018,
                        51.718766758309
                    ],
                    [
                        -3.4054234977632,
                        51.722598352261
                    ],
                    [
                        -3.4115820536808,
                        51.731278874958
                    ],
                    [
                        -3.4128791667327,
                        51.733403316504
                    ],
                    [
                        -3.4122038468567,
                        51.733573287441
                    ],
                    [
                        -3.4134770095845,
                        51.73525201981
                    ],
                    [
                        -3.4148787690596,
                        51.73626919634
                    ],
                    [
                        -3.4140269662135,
                        51.737791861247
                    ],
                    [
                        -3.4126437890773,
                        51.738114219381
                    ],
                    [
                        -3.41172986915,
                        51.736950884496
                    ],
                    [
                        -3.4080885796999,
                        51.735633234418
                    ],
                    [
                        -3.4078795775499,
                        51.736037669537
                    ],
                    [
                        -3.4031243551954,
                        51.738677879627
                    ],
                    [
                        -3.4004313997124,
                        51.73950218041
                    ],
                    [
                        -3.3985930566286,
                        51.739394597809
                    ],
                    [
                        -3.3979251546862,
                        51.739668701461
                    ],
                    [
                        -3.398086475891,
                        51.73935836602
                    ],
                    [
                        -3.3974938727083,
                        51.739491300384
                    ],
                    [
                        -3.3960845918573,
                        51.738549538044
                    ],
                    [
                        -3.3954743834206,
                        51.738768991924
                    ],
                    [
                        -3.3915797770071,
                        51.737916014619
                    ],
                    [
                        -3.3906115971225,
                        51.737939167471
                    ],
                    [
                        -3.3872036250121,
                        51.736797945012
                    ],
                    [
                        -3.3852336694,
                        51.736786120814
                    ],
                    [
                        -3.3840668158645,
                        51.735520352742
                    ],
                    [
                        -3.3815937544087,
                        51.737386466911
                    ],
                    [
                        -3.3807781531533,
                        51.737568695901
                    ],
                    [
                        -3.3799040810288,
                        51.737305617475
                    ],
                    [
                        -3.3785537997261,
                        51.737574135832
                    ],
                    [
                        -3.3781601342223,
                        51.737154345974
                    ],
                    [
                        -3.3774630988552,
                        51.737283009169
                    ],
                    [
                        -3.374954297337,
                        51.73898575155
                    ],
                    [
                        -3.3721822535363,
                        51.735687635228
                    ],
                    [
                        -3.3702900780211,
                        51.73245292615
                    ],
                    [
                        -3.3666134728063,
                        51.732984001046
                    ],
                    [
                        -3.3663402576456,
                        51.73410394768
                    ],
                    [
                        -3.3633038128998,
                        51.736471667231
                    ],
                    [
                        -3.3618548928347,
                        51.736592775058
                    ],
                    [
                        -3.3612930412059,
                        51.736931978926
                    ],
                    [
                        -3.3596357418425,
                        51.73681809302
                    ],
                    [
                        -3.3597907754532,
                        51.739618107718
                    ],
                    [
                        -3.3587286628884,
                        51.7397463882
                    ],
                    [
                        -3.3581390528412,
                        51.740417690555
                    ],
                    [
                        -3.3572182666541,
                        51.740526340149
                    ],
                    [
                        -3.3565198602063,
                        51.741096385755
                    ],
                    [
                        -3.3543058946828,
                        51.74189071496
                    ],
                    [
                        -3.3494218124481,
                        51.742615891505
                    ],
                    [
                        -3.3508956351411,
                        51.743953100628
                    ],
                    [
                        -3.3491517940398,
                        51.744442502628
                    ],
                    [
                        -3.3443828580574,
                        51.744667108393
                    ],
                    [
                        -3.3453316739683,
                        51.743206791924
                    ],
                    [
                        -3.344725576766,
                        51.742209361341
                    ],
                    [
                        -3.34203443396,
                        51.742062096285
                    ],
                    [
                        -3.3395235517055,
                        51.740908345936
                    ],
                    [
                        -3.3335927881357,
                        51.739539845212
                    ],
                    [
                        -3.3325264263781,
                        51.738246355247
                    ],
                    [
                        -3.3291419742091,
                        51.736672487546
                    ],
                    [
                        -3.3277804478958,
                        51.735282486178
                    ],
                    [
                        -3.3274472173663,
                        51.734338530579
                    ],
                    [
                        -3.326273134517,
                        51.734400345514
                    ],
                    [
                        -3.3245686571083,
                        51.733558173696
                    ],
                    [
                        -3.3215779470242,
                        51.732950748943
                    ],
                    [
                        -3.3211943885515,
                        51.732411067566
                    ],
                    [
                        -3.3194326693016,
                        51.732133242456
                    ],
                    [
                        -3.3187375551948,
                        51.731535009317
                    ],
                    [
                        -3.3188142078949,
                        51.730686235313
                    ],
                    [
                        -3.3179390071967,
                        51.730466769495
                    ],
                    [
                        -3.3177707455893,
                        51.72966030668
                    ],
                    [
                        -3.3182539920329,
                        51.729298815314
                    ],
                    [
                        -3.3166683594455,
                        51.727502079709
                    ],
                    [
                        -3.3178466695692,
                        51.725799333549
                    ],
                    [
                        -3.3190385811142,
                        51.724865209792
                    ],
                    [
                        -3.3192469413118,
                        51.723269546032
                    ],
                    [
                        -3.3188555170854,
                        51.722754222484
                    ],
                    [
                        -3.3197580666287,
                        51.722476134365
                    ],
                    [
                        -3.320465545198,
                        51.720969271763
                    ],
                    [
                        -3.3213025314708,
                        51.721125307304
                    ],
                    [
                        -3.3218001268561,
                        51.720813093177
                    ],
                    [
                        -3.3214278875178,
                        51.720211241979
                    ],
                    [
                        -3.3235605756085,
                        51.719128911192
                    ],
                    [
                        -3.323176356277,
                        51.718513712788
                    ],
                    [
                        -3.32367996461,
                        51.718160960086
                    ],
                    [
                        -3.3241265604185,
                        51.716154377762
                    ],
                    [
                        -3.3238522668681,
                        51.71538688182
                    ],
                    [
                        -3.3228840220139,
                        51.71479714535
                    ],
                    [
                        -3.3239401283115,
                        51.713885178773
                    ],
                    [
                        -3.3232421504242,
                        51.713429072426
                    ],
                    [
                        -3.3239212610861,
                        51.7118020166
                    ],
                    [
                        -3.3235537936046,
                        51.710618355093
                    ],
                    [
                        -3.3228303300863,
                        51.710725413481
                    ],
                    [
                        -3.32273674854,
                        51.710196856592
                    ],
                    [
                        -3.3217865836187,
                        51.709974667781
                    ],
                    [
                        -3.3212957016901,
                        51.707086663152
                    ],
                    [
                        -3.3204724185089,
                        51.706547427955
                    ],
                    [
                        -3.3206711292755,
                        51.705369978868
                    ],
                    [
                        -3.3200560941658,
                        51.704923711052
                    ],
                    [
                        -3.3203919348395,
                        51.704628605062
                    ],
                    [
                        -3.3179457127818,
                        51.702919782018
                    ],
                    [
                        -3.3192444728343,
                        51.701997938709
                    ],
                    [
                        -3.3210168108432,
                        51.701587778219
                    ],
                    [
                        -3.3222540079502,
                        51.702925309908
                    ],
                    [
                        -3.323878100193,
                        51.70388081682
                    ],
                    [
                        -3.3244697324728,
                        51.703624177408
                    ],
                    [
                        -3.3250294544159,
                        51.703959549186
                    ],
                    [
                        -3.3261082492855,
                        51.703536453155
                    ],
                    [
                        -3.3266127182241,
                        51.703912004762
                    ],
                    [
                        -3.32776622515,
                        51.703520419703
                    ],
                    [
                        -3.3282178732935,
                        51.704216666364
                    ],
                    [
                        -3.3288183032094,
                        51.704112764525
                    ],
                    [
                        -3.3287068655077,
                        51.703075482875
                    ],
                    [
                        -3.3293169947051,
                        51.702661254671
                    ],
                    [
                        -3.3315929306378,
                        51.702746072006
                    ],
                    [
                        -3.337576569917,
                        51.70190299569
                    ],
                    [
                        -3.3385527081415,
                        51.701929640355
                    ],
                    [
                        -3.340087402226,
                        51.702493904404
                    ],
                    [
                        -3.3421029748952,
                        51.701555532972
                    ],
                    [
                        -3.3443033085345,
                        51.701434158082
                    ],
                    [
                        -3.3443795712451,
                        51.70078498178
                    ],
                    [
                        -3.3465192271925,
                        51.701009542036
                    ],
                    [
                        -3.3489598805469,
                        51.702109098632
                    ],
                    [
                        -3.3503035494923,
                        51.702182676812
                    ],
                    [
                        -3.3517918546173,
                        51.701719567105
                    ],
                    [
                        -3.3517334231267,
                        51.700875916011
                    ],
                    [
                        -3.3568250147001,
                        51.701095051673
                    ],
                    [
                        -3.3562469148515,
                        51.699039024095
                    ],
                    [
                        -3.362143816343,
                        51.699241432968
                    ],
                    [
                        -3.3674926301447,
                        51.698589418452
                    ]
                ]
            ]
        ]
    }
}