{
    "type": "Feature",
    "properties": {
        "gml_id": "id4cb449a8-b664-492e-a49f-686f8b445504",
        "PAR15CD": "W04000007",
        "PAR15NM": "Bryngwran",
        "PAR15NMW": "Bryngwran",
        "LAD15CD": "W06000001",
        "LAD15NM": "Isle of Anglesey"
    },
    "geometry": {
        "type": "MultiPolygon",
        "coordinates": [
            [
                [
                    [
                        -4.45668616899,
                        53.237600374223
                    ],
                    [
                        -4.4581913392631,
                        53.239256062823
                    ],
                    [
                        -4.4567626098131,
                        53.241419134001
                    ],
                    [
                        -4.4570715647821,
                        53.242651741143
                    ],
                    [
                        -4.4624113333973,
                        53.244206649226
                    ],
                    [
                        -4.4632950064206,
                        53.246255445629
                    ],
                    [
                        -4.4638515992605,
                        53.246446236739
                    ],
                    [
                        -4.464546191324,
                        53.245960733567
                    ],
                    [
                        -4.4647455910409,
                        53.247082300202
                    ],
                    [
                        -4.4633773769839,
                        53.251287883517
                    ],
                    [
                        -4.4646265968099,
                        53.251425686738
                    ],
                    [
                        -4.4682868032867,
                        53.251022635423
                    ],
                    [
                        -4.4740858730561,
                        53.251756512524
                    ],
                    [
                        -4.4748492435078,
                        53.251008777344
                    ],
                    [
                        -4.4758746617289,
                        53.251527841313
                    ],
                    [
                        -4.4764324284881,
                        53.251425438247
                    ],
                    [
                        -4.4779156817818,
                        53.250735545782
                    ],
                    [
                        -4.4789263900838,
                        53.249703912723
                    ],
                    [
                        -4.4798730284503,
                        53.249508884252
                    ],
                    [
                        -4.4804104081136,
                        53.250194513451
                    ],
                    [
                        -4.4813315883531,
                        53.250491820778
                    ],
                    [
                        -4.4861743860738,
                        53.250218229733
                    ],
                    [
                        -4.4934753476463,
                        53.251536609948
                    ],
                    [
                        -4.4971878492262,
                        53.2518292908
                    ],
                    [
                        -4.4977045107167,
                        53.252308481091
                    ],
                    [
                        -4.4990285275975,
                        53.252389510189
                    ],
                    [
                        -4.4973177510331,
                        53.258560078222
                    ],
                    [
                        -4.4961111957009,
                        53.260472612594
                    ],
                    [
                        -4.4966419952029,
                        53.26101265171
                    ],
                    [
                        -4.494242190544,
                        53.264144191147
                    ],
                    [
                        -4.4901964279818,
                        53.266907281678
                    ],
                    [
                        -4.4884654626213,
                        53.268218390563
                    ],
                    [
                        -4.4885112000235,
                        53.268876487965
                    ],
                    [
                        -4.4873153443919,
                        53.269693577111
                    ],
                    [
                        -4.4879563262474,
                        53.270219665877
                    ],
                    [
                        -4.4867754290479,
                        53.271837549077
                    ],
                    [
                        -4.4841271224414,
                        53.271380289265
                    ],
                    [
                        -4.4824310697117,
                        53.270712525131
                    ],
                    [
                        -4.4802900699868,
                        53.275671667264
                    ],
                    [
                        -4.4777212579033,
                        53.275839291445
                    ],
                    [
                        -4.4777855400243,
                        53.275576312816
                    ],
                    [
                        -4.4771738071574,
                        53.275425391643
                    ],
                    [
                        -4.4768546655197,
                        53.276805870612
                    ],
                    [
                        -4.4756819240861,
                        53.277615164655
                    ],
                    [
                        -4.4725757766358,
                        53.276922597762
                    ],
                    [
                        -4.4724332106362,
                        53.277285200632
                    ],
                    [
                        -4.4699460471432,
                        53.276452048421
                    ],
                    [
                        -4.4694453778467,
                        53.277524275419
                    ],
                    [
                        -4.4688426106712,
                        53.277580820555
                    ],
                    [
                        -4.4677322668585,
                        53.278434596678
                    ],
                    [
                        -4.4655714839037,
                        53.282695250516
                    ],
                    [
                        -4.4645363667989,
                        53.283034945301
                    ],
                    [
                        -4.4617379636003,
                        53.283784195862
                    ],
                    [
                        -4.4616599542493,
                        53.283236451129
                    ],
                    [
                        -4.4601467131732,
                        53.28288018098
                    ],
                    [
                        -4.4625247296234,
                        53.279152810224
                    ],
                    [
                        -4.4615180776082,
                        53.278394976866
                    ],
                    [
                        -4.4606826976511,
                        53.279154893318
                    ],
                    [
                        -4.4538739461064,
                        53.278741430826
                    ],
                    [
                        -4.4522779744002,
                        53.279110548275
                    ],
                    [
                        -4.4498280892485,
                        53.2783993895
                    ],
                    [
                        -4.4489160231981,
                        53.279028629037
                    ],
                    [
                        -4.4426136221358,
                        53.276654854677
                    ],
                    [
                        -4.4403563078348,
                        53.277527378397
                    ],
                    [
                        -4.4397261586514,
                        53.277314604657
                    ],
                    [
                        -4.4389346357942,
                        53.277613125229
                    ],
                    [
                        -4.4369338643339,
                        53.277486820707
                    ],
                    [
                        -4.4359223350962,
                        53.276713590263
                    ],
                    [
                        -4.4351004388454,
                        53.276742075333
                    ],
                    [
                        -4.4335315226696,
                        53.275503687079
                    ],
                    [
                        -4.4308902794215,
                        53.275877673642
                    ],
                    [
                        -4.4302531015099,
                        53.276834728813
                    ],
                    [
                        -4.428853238132,
                        53.27704039058
                    ],
                    [
                        -4.4278478219324,
                        53.277562577267
                    ],
                    [
                        -4.4270514699656,
                        53.278703576634
                    ],
                    [
                        -4.4257353905782,
                        53.279436167501
                    ],
                    [
                        -4.4195993727106,
                        53.281974989565
                    ],
                    [
                        -4.4183287576634,
                        53.281949529681
                    ],
                    [
                        -4.4171556111037,
                        53.282826575465
                    ],
                    [
                        -4.4123848754346,
                        53.281389369863
                    ],
                    [
                        -4.4116821475754,
                        53.282389904989
                    ],
                    [
                        -4.4109991351211,
                        53.282489138403
                    ],
                    [
                        -4.4093080615693,
                        53.283736221356
                    ],
                    [
                        -4.4070010705111,
                        53.282222897267
                    ],
                    [
                        -4.4040288971901,
                        53.280856015695
                    ],
                    [
                        -4.4030101543757,
                        53.279838101326
                    ],
                    [
                        -4.4021311993782,
                        53.279706569908
                    ],
                    [
                        -4.4022656941099,
                        53.278868596125
                    ],
                    [
                        -4.4025509001089,
                        53.278684825333
                    ],
                    [
                        -4.4049856580018,
                        53.27930105118
                    ],
                    [
                        -4.405700217915,
                        53.278882933817
                    ],
                    [
                        -4.4064117439114,
                        53.279185052184
                    ],
                    [
                        -4.4085039441985,
                        53.277470462603
                    ],
                    [
                        -4.4111046463508,
                        53.276105187989
                    ],
                    [
                        -4.4118193332382,
                        53.275185331678
                    ],
                    [
                        -4.4114578651319,
                        53.274786252722
                    ],
                    [
                        -4.4140455089516,
                        53.273007588443
                    ],
                    [
                        -4.4156978216644,
                        53.272439140233
                    ],
                    [
                        -4.416770818542,
                        53.271652248405
                    ],
                    [
                        -4.4181874731421,
                        53.272171063602
                    ],
                    [
                        -4.4200502991367,
                        53.268853319528
                    ],
                    [
                        -4.420076264879,
                        53.267746894716
                    ],
                    [
                        -4.421119971351,
                        53.266816699624
                    ],
                    [
                        -4.4218332272129,
                        53.266620586696
                    ],
                    [
                        -4.4224771119704,
                        53.264694204553
                    ],
                    [
                        -4.4246753967542,
                        53.262810824108
                    ],
                    [
                        -4.4258264233568,
                        53.257953804544
                    ],
                    [
                        -4.4281924411674,
                        53.256657650965
                    ],
                    [
                        -4.4309930288199,
                        53.255809329569
                    ],
                    [
                        -4.4348278578845,
                        53.252768464123
                    ],
                    [
                        -4.4322897056256,
                        53.2514473686
                    ],
                    [
                        -4.4308465495013,
                        53.251562236912
                    ],
                    [
                        -4.4294208469358,
                        53.252434679346
                    ],
                    [
                        -4.4263169629201,
                        53.25300682316
                    ],
                    [
                        -4.4242218142297,
                        53.251244065283
                    ],
                    [
                        -4.424947170368,
                        53.249200020063
                    ],
                    [
                        -4.4243626940533,
                        53.248540282007
                    ],
                    [
                        -4.4260227222634,
                        53.247782709358
                    ],
                    [
                        -4.4270798602046,
                        53.246862070591
                    ],
                    [
                        -4.4297641392056,
                        53.246722839845
                    ],
                    [
                        -4.4318518847297,
                        53.245078930152
                    ],
                    [
                        -4.4342848847022,
                        53.243367687501
                    ],
                    [
                        -4.4373863247932,
                        53.243926458382
                    ],
                    [
                        -4.4387756042974,
                        53.244792641219
                    ],
                    [
                        -4.4401337483466,
                        53.243741643513
                    ],
                    [
                        -4.4430506177884,
                        53.242743191194
                    ],
                    [
                        -4.4441522763339,
                        53.241718084946
                    ],
                    [
                        -4.4437639093983,
                        53.241530945102
                    ],
                    [
                        -4.4454226068219,
                        53.240865731515
                    ],
                    [
                        -4.4476626880193,
                        53.239043980191
                    ],
                    [
                        -4.4507900934801,
                        53.238958102518
                    ],
                    [
                        -4.4547231690041,
                        53.238311579691
                    ],
                    [
                        -4.45668616899,
                        53.237600374223
                    ]
                ]
            ]
        ]
    }
}